tests/__init__.py
tests/test_authenticate_x.py
tests/test_delete_all_x_posts.py
tests/test_delete_posts_from_json.py
xcleaner/__init__.py
xcleaner/authenticate_x.py
xcleaner/delete_all_x_posts.py
xcleaner/main.py
xcleaner-0.1.7.dist-info/METADATA
xcleaner-0.1.7.dist-info/WHEEL
xcleaner-0.1.7.dist-info/entry_points.txt
xcleaner-0.1.7.dist-info/top_level.txt
xcleaner-0.1.7.dist-info/RECORD
