Metadata-Version: 2.4
Name: xcleaner
Version: 0.1.7
Summary: Delete all posts from your X (formerly Twitter) account.
Home-page: https://www.linkedin.com/in/scotthcollins/
Author: Scott H. Collins
Author-email: scotthcollins@outlook.com
Project-URL: LinkedIn, https://www.linkedin.com/in/scotthcollins/
Requires-Python: >=3.11
Requires-Dist: tweepy
Requires-Dist: python-dotenv
Dynamic: author
Dynamic: author-email
Dynamic: description
Dynamic: description-content-type
Dynamic: home-page
Dynamic: project-url
Dynamic: requires-dist
Dynamic: requires-python
Dynamic: summary
